shipxy/BaseMethon.py
shipxy/ResponseObj.py
shipxy/Shipxy.py
shipxy/__init__.py
shipxy_api-0.3.dist-info/METADATA
shipxy_api-0.3.dist-info/WHEEL
shipxy_api-0.3.dist-info/top_level.txt
shipxy_api-0.3.dist-info/RECORD
