Metadata-Version: 2.1
Name: shipxy-api
Version: 0.3
Summary: 亿海蓝Elane船讯网sdk https://www.shipxy.com/
Author: White
Author-email: 249898979@qq.com
Requires-Dist: requests
